pylibxc2-6.0.0.dist-info/RECORD
pylibxc2-6.0.0.dist-info/AUTHORS
pylibxc2-6.0.0.dist-info/METADATA
pylibxc2-6.0.0.dist-info/top_level.txt
pylibxc2-6.0.0.dist-info/COPYING
pylibxc2-6.0.0.dist-info/WHEEL
pylibxc/libxc.so
pylibxc/__init__.py
pylibxc/structs.py
pylibxc/libxc.so.11
pylibxc/functional.py
pylibxc/flags.py
pylibxc/version.py
pylibxc/core.py
pylibxc/util.py
